lifesaver_lite_llm/__init__.py
lifesaver_lite_llm/__main__.py
lifesaver_lite_llm/cli.py
lifesaver_lite_llm/agent/orchestrator.py
lifesaver_lite_llm/core/analytics.py
lifesaver_lite_llm/core/env.py
lifesaver_lite_llm/core/parser.py
lifesaver_lite_llm/core/redact.py
lifesaver_lite_llm/core/storage.py
lifesaver_lite_llm/core/suggestions.py
lifesaver_lite_llm/core/tags.py
lifesaver_lite_llm/core/techniques.py
lifesaver_lite_llm/core/templates.py
lifesaver_lite_llm/ingest/mitmweb.py
lifesaver_lite_llm/reporting/report.py
lifesaver_lite_llm/store/context.py
lifesaver_lite_llm/utils/magic_cli.py
lifesaver_lite_llm/web/__init__.py
lifesaver_lite_llm/web/app.py
lifesaver_lite_llm-0.1.1.dist-info/licenses/LICENSE
lifesaver_lite_llm-0.1.1.dist-info/METADATA
lifesaver_lite_llm-0.1.1.dist-info/WHEEL
lifesaver_lite_llm-0.1.1.dist-info/entry_points.txt
lifesaver_lite_llm-0.1.1.dist-info/top_level.txt
lifesaver_lite_llm-0.1.1.dist-info/RECORD
