Metadata-Version: 2.4
Name: lifesaver-lite-llm
Version: 0.1.1
Summary: Lightweight LLM usage analysis and dashboard with mitmweb ingestion
Author-email: Maintainers <maintainers@example.com>
License: MIT License
Project-URL: Homepage, https://github.com/your-org/lifesaver-lite-llm
Project-URL: Repository, https://github.com/your-org/lifesaver-lite-llm
Classifier: Programming Language :: Python :: 3
Classifier: License :: OSI Approved :: MIT License
Classifier: Operating System :: OS Independent
Requires-Python: >=3.10
License-File: LICENSE
Dynamic: license-file
